<annotation>
	<frame>12-8GOPR0192314</frame>
	<object>
		<name>holothurian</name>
		<bndbox>
			<xmin>873</xmin>
			<ymin>317</ymin>
			<xmax>1158</xmax>
			<ymax>491</ymax>
		</bndbox>
	</object>
	<object>
		<name>holothurian</name>
		<bndbox>
			<xmin>844</xmin>
			<ymin>485</ymin>
			<xmax>1142</xmax>
			<ymax>670</ymax>
		</bndbox>
	</object>
	<object>
		<name>holothurian</name>
		<bndbox>
			<xmin>875</xmin>
			<ymin>670</ymin>
			<xmax>1075</xmax>
			<ymax>880</ymax>
		</bndbox>
	</object>
<size><width>1920</width><height>1080</height></size></annotation>