<annotation>
	<frame>2019v100419</frame>
	<object>
		<name>holothurian</name>
		<bndbox>
			<xmin>1105</xmin>
			<ymin>672</ymin>
			<xmax>1843</xmax>
			<ymax>902</ymax>
		</bndbox>
	</object>
	<object>
		<name>holothurian</name>
		<bndbox>
			<xmin>10</xmin>
			<ymin>495</ymin>
			<xmax>669</xmax>
			<ymax>1087</ymax>
		</bndbox>
	</object>
	<object>
		<name>echinus</name>
		<bndbox>
			<xmin>3123</xmin>
			<ymin>450</ymin>
			<xmax>3841</xmax>
			<ymax>1109</ymax>
		</bndbox>
	</object>
	<object>
		<name>echinus</name>
		<bndbox>
			<xmin>703</xmin>
			<ymin>319</ymin>
			<xmax>1105</xmax>
			<ymax>587</ymax>
		</bndbox>
	</object>
<size><width>3840</width><height>2160</height></size></annotation>