<annotation>
	<frame>2019v200116</frame>
	<object>
		<name>scallop</name>
		<bndbox>
			<xmin>3614</xmin>
			<ymin>1446</ymin>
			<xmax>3768</xmax>
			<ymax>1578</ymax>
		</bndbox>
	</object>
	<object>
		<name>scallop</name>
		<bndbox>
			<xmin>3540</xmin>
			<ymin>1320</ymin>
			<xmax>3703</xmax>
			<ymax>1449</ymax>
		</bndbox>
	</object>
	<object>
		<name>scallop</name>
		<bndbox>
			<xmin>2960</xmin>
			<ymin>1412</ymin>
			<xmax>3116</xmax>
			<ymax>1506</ymax>
		</bndbox>
	</object>
	<object>
		<name>scallop</name>
		<bndbox>
			<xmin>3176</xmin>
			<ymin>1446</ymin>
			<xmax>3297</xmax>
			<ymax>1578</ymax>
		</bndbox>
	</object>
	<object>
		<name>scallop</name>
		<bndbox>
			<xmin>3327</xmin>
			<ymin>1488</ymin>
			<xmax>3490</xmax>
			<ymax>1645</ymax>
		</bndbox>
	</object>
	<object>
		<name>scallop</name>
		<bndbox>
			<xmin>1385</xmin>
			<ymin>1209</ymin>
			<xmax>1511</xmax>
			<ymax>1308</ymax>
		</bndbox>
	</object>
	<object>
		<name>scallop</name>
		<bndbox>
			<xmin>2110</xmin>
			<ymin>1015</ymin>
			<xmax>2215</xmax>
			<ymax>1114</ymax>
		</bndbox>
	</object>
	<object>
		<name>scallop</name>
		<bndbox>
			<xmin>1972</xmin>
			<ymin>1233</ymin>
			<xmax>2083</xmax>
			<ymax>1337</ymax>
		</bndbox>
	</object>
	<object>
		<name>starfish</name>
		<bndbox>
			<xmin>456</xmin>
			<ymin>882</ymin>
			<xmax>656</xmax>
			<ymax>1020</ymax>
		</bndbox>
	</object>
	<object>
		<name>starfish</name>
		<bndbox>
			<xmin>1328</xmin>
			<ymin>72</ymin>
			<xmax>1489</xmax>
			<ymax>181</ymax>
		</bndbox>
	</object>
	<object>
		<name>starfish</name>
		<bndbox>
			<xmin>1826</xmin>
			<ymin>138</ymin>
			<xmax>1974</xmax>
			<ymax>267</ymax>
		</bndbox>
	</object>
	<object>
		<name>starfish</name>
		<bndbox>
			<xmin>2410</xmin>
			<ymin>32</ymin>
			<xmax>2586</xmax>
			<ymax>131</ymax>
		</bndbox>
	</object>
	<object>
		<name>starfish</name>
		<bndbox>
			<xmin>2705</xmin>
			<ymin>228</ymin>
			<xmax>2846</xmax>
			<ymax>356</ymax>
		</bndbox>
	</object>
	<object>
		<name>starfish</name>
		<bndbox>
			<xmin>2638</xmin>
			<ymin>537</ymin>
			<xmax>2816</xmax>
			<ymax>681</ymax>
		</bndbox>
	</object>
	<object>
		<name>starfish</name>
		<bndbox>
			<xmin>2871</xmin>
			<ymin>661</ymin>
			<xmax>3044</xmax>
			<ymax>830</ymax>
		</bndbox>
	</object>
	<object>
		<name>starfish</name>
		<bndbox>
			<xmin>2685</xmin>
			<ymin>852</ymin>
			<xmax>2866</xmax>
			<ymax>1003</ymax>
		</bndbox>
	</object>
	<object>
		<name>starfish</name>
		<bndbox>
			<xmin>2856</xmin>
			<ymin>1248</ymin>
			<xmax>3017</xmax>
			<ymax>1409</ymax>
		</bndbox>
	</object>
	<object>
		<name>starfish</name>
		<bndbox>
			<xmin>3203</xmin>
			<ymin>599</ymin>
			<xmax>3356</xmax>
			<ymax>750</ymax>
		</bndbox>
	</object>
	<object>
		<name>starfish</name>
		<bndbox>
			<xmin>3758</xmin>
			<ymin>1414</ymin>
			<xmax>3841</xmax>
			<ymax>1545</ymax>
		</bndbox>
	</object>
	<object>
		<name>scallop</name>
		<bndbox>
			<xmin>2799</xmin>
			<ymin>2088</ymin>
			<xmax>2987</xmax>
			<ymax>2161</ymax>
		</bndbox>
	</object>
	<object>
		<name>scallop</name>
		<bndbox>
			<xmin>2750</xmin>
			<ymin>1818</ymin>
			<xmax>2938</xmax>
			<ymax>2001</ymax>
		</bndbox>
	</object>
	<object>
		<name>scallop</name>
		<bndbox>
			<xmin>3243</xmin>
			<ymin>1221</ymin>
			<xmax>3379</xmax>
			<ymax>1332</ymax>
		</bndbox>
	</object>
	<object>
		<name>holothurian</name>
		<bndbox>
			<xmin>2264</xmin>
			<ymin>1360</ymin>
			<xmax>2524</xmax>
			<ymax>1545</ymax>
		</bndbox>
	</object>
<size><width>3840</width><height>2160</height></size></annotation>