<annotation>
	<frame>2019v200491</frame>
	<object>
		<name>scallop</name>
		<bndbox>
			<xmin>1320</xmin>
			<ymin>834</ymin>
			<xmax>1468</xmax>
			<ymax>917</ymax>
		</bndbox>
	</object>
	<object>
		<name>scallop</name>
		<bndbox>
			<xmin>1405</xmin>
			<ymin>1501</ymin>
			<xmax>1708</xmax>
			<ymax>1759</ymax>
		</bndbox>
	</object>
	<object>
		<name>starfish</name>
		<bndbox>
			<xmin>2041</xmin>
			<ymin>631</ymin>
			<xmax>2257</xmax>
			<ymax>752</ymax>
		</bndbox>
	</object>
	<object>
		<name>scallop</name>
		<bndbox>
			<xmin>2232</xmin>
			<ymin>561</ymin>
			<xmax>2334</xmax>
			<ymax>656</ymax>
		</bndbox>
	</object>
	<object>
		<name>scallop</name>
		<bndbox>
			<xmin>3161</xmin>
			<ymin>707</ymin>
			<xmax>3391</xmax>
			<ymax>827</ymax>
		</bndbox>
	</object>
	<object>
		<name>scallop</name>
		<bndbox>
			<xmin>1741</xmin>
			<ymin>1681</ymin>
			<xmax>1851</xmax>
			<ymax>1783</ymax>
		</bndbox>
	</object>
	<object>
		<name>scallop</name>
		<bndbox>
			<xmin>1272</xmin>
			<ymin>1300</ymin>
			<xmax>1485</xmax>
			<ymax>1450</ymax>
		</bndbox>
	</object>
	<object>
		<name>scallop</name>
		<bndbox>
			<xmin>1888</xmin>
			<ymin>363</ymin>
			<xmax>1926</xmax>
			<ymax>416</ymax>
		</bndbox>
	</object>
<size><width>3840</width><height>2160</height></size></annotation>