<annotation>
	<frame>2019v201143</frame>
	<object>
		<name>scallop</name>
		<bndbox>
			<xmin>2220</xmin>
			<ymin>1007</ymin>
			<xmax>2390</xmax>
			<ymax>1145</ymax>
		</bndbox>
	</object>
	<object>
		<name>scallop</name>
		<bndbox>
			<xmin>3478</xmin>
			<ymin>913</ymin>
			<xmax>3768</xmax>
			<ymax>1121</ymax>
		</bndbox>
	</object>
	<object>
		<name>scallop</name>
		<bndbox>
			<xmin>3765</xmin>
			<ymin>1851</ymin>
			<xmax>3765</xmax>
			<ymax>1871</ymax>
		</bndbox>
	</object>
	<object>
		<name>scallop</name>
		<bndbox>
			<xmin>3463</xmin>
			<ymin>1609</ymin>
			<xmax>3840</xmax>
			<ymax>1842</ymax>
		</bndbox>
	</object>
	<object>
		<name>scallop</name>
		<bndbox>
			<xmin>3258</xmin>
			<ymin>1386</ymin>
			<xmax>3617</xmax>
			<ymax>1651</ymax>
		</bndbox>
	</object>
	<object>
		<name>scallop</name>
		<bndbox>
			<xmin>2717</xmin>
			<ymin>722</ymin>
			<xmax>2906</xmax>
			<ymax>908</ymax>
		</bndbox>
	</object>
	<object>
		<name>scallop</name>
		<bndbox>
			<xmin>2713</xmin>
			<ymin>875</ymin>
			<xmax>2968</xmax>
			<ymax>1061</ymax>
		</bndbox>
	</object>
	<object>
		<name>scallop</name>
		<bndbox>
			<xmin>2571</xmin>
			<ymin>712</ymin>
			<xmax>2772</xmax>
			<ymax>905</ymax>
		</bndbox>
	</object>
	<object>
		<name>scallop</name>
		<bndbox>
			<xmin>1209</xmin>
			<ymin>1257</ymin>
			<xmax>1437</xmax>
			<ymax>1465</ymax>
		</bndbox>
	</object>
	<object>
		<name>scallop</name>
		<bndbox>
			<xmin>1449</xmin>
			<ymin>1314</ymin>
			<xmax>1650</xmax>
			<ymax>1505</ymax>
		</bndbox>
	</object>
	<object>
		<name>scallop</name>
		<bndbox>
			<xmin>1630</xmin>
			<ymin>1153</ymin>
			<xmax>1870</xmax>
			<ymax>1349</ymax>
		</bndbox>
	</object>
	<object>
		<name>scallop</name>
		<bndbox>
			<xmin>2036</xmin>
			<ymin>1136</ymin>
			<xmax>2249</xmax>
			<ymax>1299</ymax>
		</bndbox>
	</object>
	<object>
		<name>scallop</name>
		<bndbox>
			<xmin>1818</xmin>
			<ymin>967</ymin>
			<xmax>2011</xmax>
			<ymax>1093</ymax>
		</bndbox>
	</object>
	<object>
		<name>scallop</name>
		<bndbox>
			<xmin>1541</xmin>
			<ymin>1388</ymin>
			<xmax>1727</xmax>
			<ymax>1532</ymax>
		</bndbox>
	</object>
	<object>
		<name>holothurian</name>
		<bndbox>
			<xmin>1788</xmin>
			<ymin>1648</ymin>
			<xmax>2078</xmax>
			<ymax>1943</ymax>
		</bndbox>
	</object>
	<object>
		<name>scallop</name>
		<bndbox>
			<xmin>2049</xmin>
			<ymin>1658</ymin>
			<xmax>2321</xmax>
			<ymax>1881</ymax>
		</bndbox>
	</object>
	<object>
		<name>scallop</name>
		<bndbox>
			<xmin>1850</xmin>
			<ymin>1306</ymin>
			<xmax>2054</xmax>
			<ymax>1465</ymax>
		</bndbox>
	</object>
	<object>
		<name>scallop</name>
		<bndbox>
			<xmin>3026</xmin>
			<ymin>598</ymin>
			<xmax>3204</xmax>
			<ymax>733</ymax>
		</bndbox>
	</object>
<size><width>3840</width><height>2160</height></size></annotation>