<annotation>
	<frame>2019v201125</frame>
	<object>
		<name>scallop</name>
		<bndbox>
			<xmin>1437</xmin>
			<ymin>776</ymin>
			<xmax>1610</xmax>
			<ymax>895</ymax>
		</bndbox>
	</object>
	<object>
		<name>scallop</name>
		<bndbox>
			<xmin>302</xmin>
			<ymin>1056</ymin>
			<xmax>453</xmax>
			<ymax>1185</ymax>
		</bndbox>
	</object>
	<object>
		<name>scallop</name>
		<bndbox>
			<xmin>1065</xmin>
			<ymin>1076</ymin>
			<xmax>1201</xmax>
			<ymax>1222</ymax>
		</bndbox>
	</object>
	<object>
		<name>scallop</name>
		<bndbox>
			<xmin>3101</xmin>
			<ymin>1108</ymin>
			<xmax>3334</xmax>
			<ymax>1292</ymax>
		</bndbox>
	</object>
	<object>
		<name>scallop</name>
		<bndbox>
			<xmin>3045</xmin>
			<ymin>1661</ymin>
			<xmax>3285</xmax>
			<ymax>1886</ymax>
		</bndbox>
	</object>
	<object>
		<name>scallop</name>
		<bndbox>
			<xmin>2108</xmin>
			<ymin>1663</ymin>
			<xmax>2338</xmax>
			<ymax>1894</ymax>
		</bndbox>
	</object>
	<object>
		<name>scallop</name>
		<bndbox>
			<xmin>1504</xmin>
			<ymin>1371</ymin>
			<xmax>1707</xmax>
			<ymax>1549</ymax>
		</bndbox>
	</object>
	<object>
		<name>scallop</name>
		<bndbox>
			<xmin>1707</xmin>
			<ymin>1683</ymin>
			<xmax>1999</xmax>
			<ymax>1988</ymax>
		</bndbox>
	</object>
	<object>
		<name>scallop</name>
		<bndbox>
			<xmin>1556</xmin>
			<ymin>1616</ymin>
			<xmax>1759</xmax>
			<ymax>1869</ymax>
		</bndbox>
	</object>
	<object>
		<name>scallop</name>
		<bndbox>
			<xmin>2024</xmin>
			<ymin>630</ymin>
			<xmax>2175</xmax>
			<ymax>732</ymax>
		</bndbox>
	</object>
	<object>
		<name>scallop</name>
		<bndbox>
			<xmin>2031</xmin>
			<ymin>729</ymin>
			<xmax>2182</xmax>
			<ymax>828</ymax>
		</bndbox>
	</object>
	<object>
		<name>scallop</name>
		<bndbox>
			<xmin>2088</xmin>
			<ymin>841</ymin>
			<xmax>2222</xmax>
			<ymax>942</ymax>
		</bndbox>
	</object>
	<object>
		<name>scallop</name>
		<bndbox>
			<xmin>1848</xmin>
			<ymin>1111</ymin>
			<xmax>2009</xmax>
			<ymax>1287</ymax>
		</bndbox>
	</object>
	<object>
		<name>scallop</name>
		<bndbox>
			<xmin>1749</xmin>
			<ymin>791</ymin>
			<xmax>1893</xmax>
			<ymax>927</ymax>
		</bndbox>
	</object>
	<object>
		<name>scallop</name>
		<bndbox>
			<xmin>1469</xmin>
			<ymin>920</ymin>
			<xmax>1672</xmax>
			<ymax>1061</ymax>
		</bndbox>
	</object>
	<object>
		<name>scallop</name>
		<bndbox>
			<xmin>1325</xmin>
			<ymin>1061</ymin>
			<xmax>1518</xmax>
			<ymax>1242</ymax>
		</bndbox>
	</object>
<size><width>3840</width><height>2160</height></size></annotation>