<annotation>
   <frame>GOPR0293_12499</frame>
   <object>
      <name>echinus</name>
      <bndbox>
         <xmin>1081</xmin>
         <ymin>221</ymin>
         <xmax>1154</xmax>
         <ymax>293</ymax>
      </bndbox>
   </object>
   <object>
      <name>echinus</name>
      <bndbox>
         <xmin>1141</xmin>
         <ymin>200</ymin>
         <xmax>1223</xmax>
         <ymax>284</ymax>
      </bndbox>
   </object>
   <object>
      <name>echinus</name>
      <bndbox>
         <xmin>280</xmin>
         <ymin>882</ymin>
         <xmax>353</xmax>
         <ymax>966</ymax>
      </bndbox>
   </object>
   <object>
      <name>echinus</name>
      <bndbox>
         <xmin>1831</xmin>
         <ymin>448</ymin>
         <xmax>1920</xmax>
         <ymax>525</ymax>
      </bndbox>
   </object>
   <object>
      <name>echinus</name>
      <bndbox>
         <xmin>1849</xmin>
         <ymin>308</ymin>
         <xmax>1920</xmax>
         <ymax>442</ymax>
      </bndbox>
   </object>
   <object>
      <name>echinus</name>
      <bndbox>
         <xmin>1307</xmin>
         <ymin>374</ymin>
         <xmax>1395</xmax>
         <ymax>452</ymax>
      </bndbox>
   </object>
   <object>
      <name>echinus</name>
      <bndbox>
         <xmin>1407</xmin>
         <ymin>293</ymin>
         <xmax>1480</xmax>
         <ymax>353</ymax>
      </bndbox>
   </object>
   <object>
      <name>echinus</name>
      <bndbox>
         <xmin>1357</xmin>
         <ymin>203</ymin>
         <xmax>1437</xmax>
         <ymax>269</ymax>
      </bndbox>
   </object>
   <object>
      <name>holothurian</name>
      <bndbox>
         <xmin>716</xmin>
         <ymin>570</ymin>
         <xmax>820</xmax>
         <ymax>630</ymax>
      </bndbox>
   </object>
   <object>
      <name>holothurian</name>
      <bndbox>
         <xmin>902</xmin>
         <ymin>950</ymin>
         <xmax>996</xmax>
         <ymax>1081</ymax>
      </bndbox>
   </object>
   <object>
      <name>holothurian</name>
      <bndbox>
         <xmin>846</xmin>
         <ymin>919</ymin>
         <xmax>926</xmax>
         <ymax>1081</ymax>
      </bndbox>
   </object>
<size><width>1920</width><height>1080</height></size></annotation>