<annotation>
   <frame>GOPR0294_30052</frame>
   <object>
      <name>echinus</name>
      <bndbox>
         <xmin>203</xmin>
         <ymin>234</ymin>
         <xmax>253</xmax>
         <ymax>283</ymax>
      </bndbox>
   </object>
   <object>
      <name>echinus</name>
      <bndbox>
         <xmin>202</xmin>
         <ymin>340</ymin>
         <xmax>257</xmax>
         <ymax>389</ymax>
      </bndbox>
   </object>
   <object>
      <name>echinus</name>
      <bndbox>
         <xmin>250</xmin>
         <ymin>292</ymin>
         <xmax>300</xmax>
         <ymax>348</ymax>
      </bndbox>
   </object>
   <object>
      <name>echinus</name>
      <bndbox>
         <xmin>537</xmin>
         <ymin>203</ymin>
         <xmax>580</xmax>
         <ymax>248</ymax>
      </bndbox>
   </object>
   <object>
      <name>echinus</name>
      <bndbox>
         <xmin>564</xmin>
         <ymin>344</ymin>
         <xmax>604</xmax>
         <ymax>385</ymax>
      </bndbox>
   </object>
<size><width>720</width><height>405</height></size></annotation>