<annotation>
   <frame>GP010293_3720</frame>
   <object>
      <name>echinus</name>
      <bndbox>
         <xmin>135</xmin>
         <ymin>68</ymin>
         <xmax>166</xmax>
         <ymax>93</ymax>
      </bndbox>
   </object>
   <object>
      <name>echinus</name>
      <bndbox>
         <xmin>302</xmin>
         <ymin>141</ymin>
         <xmax>328</xmax>
         <ymax>173</ymax>
      </bndbox>
   </object>
   <object>
      <name>echinus</name>
      <bndbox>
         <xmin>187</xmin>
         <ymin>257</ymin>
         <xmax>218</xmax>
         <ymax>281</ymax>
      </bndbox>
   </object>
   <object>
      <name>echinus</name>
      <bndbox>
         <xmin>95</xmin>
         <ymin>150</ymin>
         <xmax>125</xmax>
         <ymax>187</ymax>
      </bndbox>
   </object>
<size><width>720</width><height>405</height></size></annotation>