<annotation>
	<frame>YDXJ0041096</frame>
	<object>
		<name>echinus</name>
		<bndbox>
			<xmin>2108</xmin>
			<ymin>6</ymin>
			<xmax>2316</xmax>
			<ymax>128</ymax>
		</bndbox>
	</object>
	<object>
		<name>starfish</name>
		<bndbox>
			<xmin>1853</xmin>
			<ymin>1754</ymin>
			<xmax>2314</xmax>
			<ymax>2054</ymax>
		</bndbox>
	</object>
	<object>
		<name>starfish</name>
		<bndbox>
			<xmin>2227</xmin>
			<ymin>138</ymin>
			<xmax>2422</xmax>
			<ymax>272</ymax>
		</bndbox>
	</object>
	<object>
		<name>echinus</name>
		<bndbox>
			<xmin>2629</xmin>
			<ymin>1343</ymin>
			<xmax>3070</xmax>
			<ymax>1589</ymax>
		</bndbox>
	</object>
	<object>
		<name>echinus</name>
		<bndbox>
			<xmin>2574</xmin>
			<ymin>1016</ymin>
			<xmax>2857</xmax>
			<ymax>1187</ymax>
		</bndbox>
	</object>
<size><width>3840</width><height>2160</height></size></annotation>