<annotation>
   <frame>YN010001_4534</frame>
   <object>
      <name>echinus</name>
      <bndbox>
         <xmin>438</xmin>
         <ymin>112</ymin>
         <xmax>468</xmax>
         <ymax>145</ymax>
      </bndbox>
   </object>
   <object>
      <name>echinus</name>
      <bndbox>
         <xmin>465</xmin>
         <ymin>135</ymin>
         <xmax>497</xmax>
         <ymax>170</ymax>
      </bndbox>
   </object>
   <object>
      <name>echinus</name>
      <bndbox>
         <xmin>39</xmin>
         <ymin>247</ymin>
         <xmax>91</xmax>
         <ymax>306</ymax>
      </bndbox>
   </object>
   <object>
      <name>echinus</name>
      <bndbox>
         <xmin>1</xmin>
         <ymin>356</ymin>
         <xmax>69</xmax>
         <ymax>406</ymax>
      </bndbox>
   </object>
   <object>
      <name>starfish</name>
      <bndbox>
         <xmin>199</xmin>
         <ymin>227</ymin>
         <xmax>258</xmax>
         <ymax>287</ymax>
      </bndbox>
   </object>
   <object>
      <name>starfish</name>
      <bndbox>
         <xmin>394</xmin>
         <ymin>270</ymin>
         <xmax>460</xmax>
         <ymax>344</ymax>
      </bndbox>
   </object>
<size><width>720</width><height>405</height></size></annotation>