<annotation>
   <frame>YN030001_3897</frame>
   <object>
      <name>echinus</name>
      <bndbox>
         <xmin>206</xmin>
         <ymin>206</ymin>
         <xmax>254</xmax>
         <ymax>247</ymax>
      </bndbox>
   </object>
   <object>
      <name>echinus</name>
      <bndbox>
         <xmin>83</xmin>
         <ymin>291</ymin>
         <xmax>130</xmax>
         <ymax>333</ymax>
      </bndbox>
   </object>
   <object>
      <name>starfish</name>
      <bndbox>
         <xmin>389</xmin>
         <ymin>218</ymin>
         <xmax>449</xmax>
         <ymax>293</ymax>
      </bndbox>
   </object>
<size><width>720</width><height>405</height></size></annotation>