<annotation>
	<frame>YN030021056</frame>
	<object>
		<name>echinus</name>
		<bndbox>
			<xmin>1043</xmin>
			<ymin>23</ymin>
			<xmax>1225</xmax>
			<ymax>140</ymax>
		</bndbox>
	</object>
	<object>
		<name>echinus</name>
		<bndbox>
			<xmin>751</xmin>
			<ymin>267</ymin>
			<xmax>972</xmax>
			<ymax>440</ymax>
		</bndbox>
	</object>
	<object>
		<name>echinus</name>
		<bndbox>
			<xmin>2277</xmin>
			<ymin>386</ymin>
			<xmax>2551</xmax>
			<ymax>560</ymax>
		</bndbox>
	</object>
	<object>
		<name>echinus</name>
		<bndbox>
			<xmin>227</xmin>
			<ymin>857</ymin>
			<xmax>466</xmax>
			<ymax>995</ymax>
		</bndbox>
	</object>
	<object>
		<name>holothurian</name>
		<bndbox>
			<xmin>236</xmin>
			<ymin>1582</ymin>
			<xmax>552</xmax>
			<ymax>1781</ymax>
		</bndbox>
	</object>
	<object>
		<name>holothurian</name>
		<bndbox>
			<xmin>1019</xmin>
			<ymin>440</ymin>
			<xmax>1246</xmax>
			<ymax>992</ymax>
		</bndbox>
	</object>
	<object>
		<name>holothurian</name>
		<bndbox>
			<xmin>901</xmin>
			<ymin>1585</ymin>
			<xmax>1237</xmax>
			<ymax>1828</ymax>
		</bndbox>
	</object>
<size><width>3840</width><height>2160</height></size></annotation>