<annotation>
	<frame>YN030040040</frame>
	<object>
		<name>echinus</name>
		<bndbox>
			<xmin>1392</xmin>
			<ymin>434</ymin>
			<xmax>1553</xmax>
			<ymax>539</ymax>
		</bndbox>
	</object>
	<object>
		<name>echinus</name>
		<bndbox>
			<xmin>1752</xmin>
			<ymin>940</ymin>
			<xmax>1917</xmax>
			<ymax>1129</ymax>
		</bndbox>
	</object>
	<object>
		<name>echinus</name>
		<bndbox>
			<xmin>1794</xmin>
			<ymin>1176</ymin>
			<xmax>1946</xmax>
			<ymax>1355</ymax>
		</bndbox>
	</object>
	<object>
		<name>echinus</name>
		<bndbox>
			<xmin>900</xmin>
			<ymin>1286</ymin>
			<xmax>1053</xmax>
			<ymax>1415</ymax>
		</bndbox>
	</object>
	<object>
		<name>echinus</name>
		<bndbox>
			<xmin>183</xmin>
			<ymin>580</ymin>
			<xmax>364</xmax>
			<ymax>738</ymax>
		</bndbox>
	</object>
	<object>
		<name>echinus</name>
		<bndbox>
			<xmin>206</xmin>
			<ymin>1170</ymin>
			<xmax>418</xmax>
			<ymax>1343</ymax>
		</bndbox>
	</object>
	<object>
		<name>echinus</name>
		<bndbox>
			<xmin>33</xmin>
			<ymin>1608</ymin>
			<xmax>284</xmax>
			<ymax>1817</ymax>
		</bndbox>
	</object>
	<object>
		<name>holothurian</name>
		<bndbox>
			<xmin>1341</xmin>
			<ymin>1873</ymin>
			<xmax>1526</xmax>
			<ymax>1987</ymax>
		</bndbox>
	</object>
<size><width>3840</width><height>2160</height></size></annotation>