<annotation>
   <frame>YN040001_3994</frame>
   <object>
      <name>holothurian</name>
      <bndbox>
         <xmin>388</xmin>
         <ymin>346</ymin>
         <xmax>432</xmax>
         <ymax>406</ymax>
      </bndbox>
   </object>
   <object>
      <name>starfish</name>
      <bndbox>
         <xmin>77</xmin>
         <ymin>229</ymin>
         <xmax>148</xmax>
         <ymax>281</ymax>
      </bndbox>
   </object>
   <object>
      <name>starfish</name>
      <bndbox>
         <xmin>153</xmin>
         <ymin>110</ymin>
         <xmax>195</xmax>
         <ymax>139</ymax>
      </bndbox>
   </object>
   <object>
      <name>starfish</name>
      <bndbox>
         <xmin>349</xmin>
         <ymin>169</ymin>
         <xmax>393</xmax>
         <ymax>208</ymax>
      </bndbox>
   </object>
   <object>
      <name>starfish</name>
      <bndbox>
         <xmin>322</xmin>
         <ymin>281</ymin>
         <xmax>365</xmax>
         <ymax>320</ymax>
      </bndbox>
   </object>
   <object>
      <name>starfish</name>
      <bndbox>
         <xmin>433</xmin>
         <ymin>267</ymin>
         <xmax>484</xmax>
         <ymax>314</ymax>
      </bndbox>
   </object>
<size><width>720</width><height>405</height></size></annotation>