<annotation>
	<frame>YN040021008</frame>
	<object>
		<name>echinus</name>
		<bndbox>
			<xmin>2244</xmin>
			<ymin>547</ymin>
			<xmax>2703</xmax>
			<ymax>905</ymax>
		</bndbox>
	</object>
	<object>
		<name>echinus</name>
		<bndbox>
			<xmin>2810</xmin>
			<ymin>231</ymin>
			<xmax>3284</xmax>
			<ymax>646</ymax>
		</bndbox>
	</object>
	<object>
		<name>echinus</name>
		<bndbox>
			<xmin>2929</xmin>
			<ymin>580</ymin>
			<xmax>3617</xmax>
			<ymax>1030</ymax>
		</bndbox>
	</object>
	<object>
		<name>echinus</name>
		<bndbox>
			<xmin>1329</xmin>
			<ymin>234</ymin>
			<xmax>1523</xmax>
			<ymax>414</ymax>
		</bndbox>
	</object>
	<object>
		<name>echinus</name>
		<bndbox>
			<xmin>1100</xmin>
			<ymin>1</ymin>
			<xmax>1336</xmax>
			<ymax>109</ymax>
		</bndbox>
	</object>
	<object>
		<name>echinus</name>
		<bndbox>
			<xmin>3173</xmin>
			<ymin>950</ymin>
			<xmax>3650</xmax>
			<ymax>1358</ymax>
		</bndbox>
	</object>
	<object>
		<name>holothurian</name>
		<bndbox>
			<xmin>239</xmin>
			<ymin>1030</ymin>
			<xmax>456</xmax>
			<ymax>1287</ymax>
		</bndbox>
	</object>
<size><width>3840</width><height>2160</height></size></annotation>