<?xml version="1.0" ?>
<annotation>
	<frame>c000792</frame>
	<object>
		<name>starfish</name>
		<bndbox>
			<xmin>807</xmin>
			<ymin>375</ymin>
			<xmax>1016</xmax>
			<ymax>517</ymax>
		</bndbox>
	</object>
	<object>
		<name>echinus</name>
		<bndbox>
			<xmin>2410</xmin>
			<ymin>329</ymin>
			<xmax>2503</xmax>
			<ymax>459</ymax>
		</bndbox>
	</object>
	<object>
		<name>scallop</name>
		<bndbox>
			<xmin>2687</xmin>
			<ymin>762</ymin>
			<xmax>2788</xmax>
			<ymax>867</ymax>
		</bndbox>
	</object>
	<object>
		<name>scallop</name>
		<bndbox>
			<xmin>2811</xmin>
			<ymin>1897</ymin>
			<xmax>2921</xmax>
			<ymax>2034</ymax>
		</bndbox>
	</object>
	<object>
		<name>scallop</name>
		<bndbox>
			<xmin>2147</xmin>
			<ymin>1805</ymin>
			<xmax>2293</xmax>
			<ymax>1985</ymax>
		</bndbox>
	</object>
	<object>
		<name>starfish</name>
		<bndbox>
			<xmin>2399</xmin>
			<ymin>1105</ymin>
			<xmax>2575</xmax>
			<ymax>1272</ymax>
		</bndbox>
	</object>
	<object>
		<name>starfish</name>
		<bndbox>
			<xmin>2029</xmin>
			<ymin>1612</ymin>
			<xmax>2204</xmax>
			<ymax>1826</ymax>
		</bndbox>
	</object>
	<object>
		<name>holothurian</name>
		<bndbox>
			<xmin>1</xmin>
			<ymin>1522</ymin>
			<xmax>778</xmax>
			<ymax>2160</ymax>
		</bndbox>
	</object>
	<size>
		<width>3840</width>
		<height>2160</height>
	</size>
</annotation>
