<?xml version="1.0" ?>
<annotation>
	<frame>c001354</frame>
	<object>
		<name>starfish</name>
		<bndbox>
			<xmin>3228</xmin>
			<ymin>1473</ymin>
			<xmax>3372</xmax>
			<ymax>1659</ymax>
		</bndbox>
	</object>
	<object>
		<name>starfish</name>
		<bndbox>
			<xmin>1906</xmin>
			<ymin>632</ymin>
			<xmax>2042</xmax>
			<ymax>795</ymax>
		</bndbox>
	</object>
	<object>
		<name>holothurian</name>
		<bndbox>
			<xmin>1728</xmin>
			<ymin>1072</ymin>
			<xmax>2020</xmax>
			<ymax>1318</ymax>
		</bndbox>
	</object>
	<object>
		<name>starfish</name>
		<bndbox>
			<xmin>2289</xmin>
			<ymin>1068</ymin>
			<xmax>2622</xmax>
			<ymax>1367</ymax>
		</bndbox>
	</object>
	<object>
		<name>holothurian</name>
		<bndbox>
			<xmin>2471</xmin>
			<ymin>46</ymin>
			<xmax>2605</xmax>
			<ymax>155</ymax>
		</bndbox>
	</object>
	<size>
		<width>3840</width>
		<height>2160</height>
	</size>
</annotation>
